README
setup.py
bin/statsdlog-server
statsdlog/__init__.py
statsdlog/daemonutils.py
statsdlog/statsdlogd.py
statsdlog.egg-info/PKG-INFO
statsdlog.egg-info/SOURCES.txt
statsdlog.egg-info/dependency_links.txt
statsdlog.egg-info/top_level.txt
test/test_statsdlogd.py