Metadata-Version: 1.1
Name: statsdlog
Version: 0.1.1
Summary: generate statsd events by monitoring a syslog udp stream
Home-page: http://github.com/pandemicsyn/statsdlog
Author: Florian Hines
Author-email: syn@ronin.io
License: Apache License, (2.0)
Keywords: statsd syslog graphite
Platform: UNKNOWN
Classifier: Development Status :: 4 - Beta
Classifier: License :: OSI Approved :: Apache Software License
Classifier: Operating System :: POSIX :: Linux
Classifier: Programming Language :: Python :: 2.6
Classifier: Environment :: No Input/Output (Daemon)
